mm_telegram/__init__.py
mm_telegram/message.py
mm_telegram/private_bot.py
mm_telegram/py.typed
mm_telegram-0.4.0.dist-info/METADATA
mm_telegram-0.4.0.dist-info/WHEEL
mm_telegram-0.4.0.dist-info/RECORD
