Metadata-Version: 2.4
Name: mm-telegram
Version: 0.4.0
Requires-Python: >=3.14
Requires-Dist: mm-http~=0.3.0
Requires-Dist: python-telegram-bot~=22.6
